broker_utils/__init__.py
broker_utils/consumer_sim.py
broker_utils/data_utils.py
broker_utils/gcp_utils.py
broker_utils/math.py
broker_utils/schema_maps.py
broker_utils/testing.py
broker_utils/types.py
broker_utils/avro_schemas/__init__.py
broker_utils/avro_schemas/elasticc.v0_9.alert.avsc
broker_utils/avro_schemas/elasticc.v0_9.brokerClassification.avsc
broker_utils/avro_schemas/elasticc.v0_9.diaForcedSource.avsc
broker_utils/avro_schemas/elasticc.v0_9.diaNondetectionLimit.avsc
broker_utils/avro_schemas/elasticc.v0_9.diaObject.avsc
broker_utils/avro_schemas/elasticc.v0_9.diaSource.avsc
broker_utils/avro_schemas/elasticc.v0_9_1.alert.avsc
broker_utils/avro_schemas/elasticc.v0_9_1.brokerClassification.avsc
broker_utils/avro_schemas/elasticc.v0_9_1.diaForcedSource.avsc
broker_utils/avro_schemas/elasticc.v0_9_1.diaNondetectionLimit.avsc
broker_utils/avro_schemas/elasticc.v0_9_1.diaObject.avsc
broker_utils/avro_schemas/elasticc.v0_9_1.diaSource.avsc
broker_utils/avro_schemas/load.py
pgb_broker_utils-0.2.47.dist-info/LICENSE.txt
pgb_broker_utils-0.2.47.dist-info/METADATA
pgb_broker_utils-0.2.47.dist-info/WHEEL
pgb_broker_utils-0.2.47.dist-info/top_level.txt
pgb_broker_utils-0.2.47.dist-info/RECORD
